Lab00/hexcode.vhd
-- 1) Aos Switchs, leds, display de 7 segmentos e os botoes
-- 2) Declarando desta forma o bit 0 se torna o mais significativo, e o bit 6 o menos  significativo, assim invertendo a ordem dos bits ao atribuir um valor
-- 3) O codigo em 7 segmentos de um digito em hexadecimal
-- 4) LEDR tera os mesmo valor de SW , ja HEX5 tera um valor com base na saida do decodificador implementado
-- 5) Ao ligar um switch o led de mesmo numero devera ser acesso, e ao apertar os botoes o valor em hex sera mostrado em um display de 7 segmentos
library ieee;
use ieee.std_logic_1164.all;

entity hexcode is
port (
  LEDR: out std_logic_vector(9 downto 0);
  SW: in std_logic_vector(9 downto 0);
  HEX5: out std_logic_vector(0 to 6);
  KEY: in std_logic_vector(3 downto 0)
  );
end entity hexcode;

architecture bhv of hexcode is
begin

  LEDR <= SW;
  
  with KEY select
  HEX5 <= "0000001" when "0000",
      "1001111" when "0001",
      "0010010" when "0010",
      "0000110" when "0011",
      "1001100" when "0100",
      "0100100" when "0101",
      "0100000" when "0110",
      "0001111" when "0111",
      "0000000" when "1000",
      "0000100" when "1001",
      "0001000" when "1010",
      "1100000" when "1011",
      "0110001" when "1100",
      "1000010" when "1101",
      "0110000" when "1110",
      "0111000" when "1111",
      "1111111" when others;

end architecture bhv;

Lab00/hexcode_tb.vhd
-- 1) Por ser um testbench ela e responsavel por gerar os sinais de entrada e analisar a saida do circuito, assim não e necessario entradas e saidas
-- 2) A instanciação e feita dentro da arquitetura, e os sinais de entrada e saida são mapeados/conectados para sinais da entidade, e utilizado uut para dizer que e a unidade sob teste.
-- Não e utilizada um pacote vhdl porque a entidade e estanciada diretamente como um componente do projeto
-- 3) A palavra work refere-se  à biblioteca de trabalho, que contém todas as entidades compiladas do projeto.
-- 4) Os pacotes std_logic_unsigned e numeric_std são utilizados para as operações aritimeticas e conversão de dados.
-- 5) range retorna o intervalo de indices do vetor, nesse caso ele e utilizado para verificar se todos os bits de sw sào iguais a 1, 
-- length retorna o tamanho do vetor ( numero total de bits), ele está sendo utilizado para garantir que a conversão em to_unsigned mantenha a quantidade de bits do vetor, 
-- event retorna true quando acontece uma transição no sinal, como uma borda de subida ou decida, no codigo ele e utilizado para monitorar as subidas do clock, essa implementação podia ser substituida por if rising_edge(clock) then que e mais clean e elegante
-- 6) sw começa em 0000000000 e incrementa até 1111111111. keys começa em 0000 e incrementa até 1111.
-- 7) Os valores de ledr e hex5 irão mudar de acordo com o valor de sw e keys, respectivamente.
library ieee;
use ieee.std_logic_1164.all;
use ieee.std_logic_unsigned.all;
use ieee.numeric_std.all;

entity hexcode_tb is
end entity hexcode_tb;

architecture tb of hexcode_tb is
	signal leds: std_logic_vector(9 downto 0);
	signal sw: std_logic_vector(9 downto 0) := (others => '0');
	signal hex: std_logic_vector(0 to 6);
	signal keys: std_logic_vector(3 downto 0) := (others => '0');
	
	signal clock: std_logic := '0';
	signal stop: std_logic;
begin

	uut: entity work.hexcode port map(LEDR => leds, SW => sw, HEX5 => hex, KEY => keys);
	
	clock <= not clock after 5 ns when stop = '0' else '0';
	stop <= '1' when sw = (sw'range => '1') and keys = (keys'range => '1') else '0';
	
	process(clock)
	begin
		if clock'event and clock = '1' and stop = '0' then
			sw <= std_logic_vector(to_unsigned(to_integer(unsigned(sw)) + 1, sw'length));
			keys <= std_logic_vector(to_unsigned(to_integer(unsigned(keys)) + 1, keys'length));
		end if;
	end process;
end architecture tb;

Lab00/hexcode.vcd
$date
  Sun Mar  9 16:06:38 2025
$end
$version
  GHDL v0
$end
$timescale
  1 fs
$end
$scope module standard $end
$upscope $end
$scope module textio $end
$upscope $end
$scope module std_logic_1164 $end
$upscope $end
$scope module std_logic_arith $end
$upscope $end
$scope module std_logic_unsigned $end
$upscope $end
$scope module numeric_std $end
$upscope $end
$scope module hexcode_tb $end
$var reg 10 ! leds[9:0] $end
$var reg 10 " sw[9:0] $end
$var reg 7 # hex[0:6] $end
$var reg 4 $ keys[3:0] $end
$var reg 1 % clock $end
$var reg 1 & stop $end
$scope module uut $end
$var reg 10 ' ledr[9:0] $end
$var reg 10 ( sw[9:0] $end
$var reg 7 ) hex5[0:6] $end
$var reg 4 * key[3:0] $end
$upscope $end
$upscope $end
$enddefinitions $end
#0
b0000000000 !
b0000000000 "
b0000001 #
b0000 $
0%
0&
b0000000000 '
b0000000000 (
b0000001 )
b0000 *
#5000000
b0000000001 !
b0000000001 "
b1001111 #
b0001 $
1%
b0000000001 '
b0000000001 (
b1001111 )
b0001 *
#10000000
0%
#15000000
b0000000010 !
b0000000010 "
b0010010 #
b0010 $
1%
b0000000010 '
b0000000010 (
b0010010 )
b0010 *
#20000000
0%
#25000000
b0000000011 !
b0000000011 "
b0000110 #
b0011 $
1%
b0000000011 '
b0000000011 (
b0000110 )
b0011 *
#30000000
0%
#35000000
b0000000100 !
b0000000100 "
b1001100 #
b0100 $
1%
b0000000100 '
b0000000100 (
b1001100 )
b0100 *
#40000000
0%
#45000000
b0000000101 !
b0000000101 "
b0100100 #
b0101 $
1%
b0000000101 '
b0000000101 (
b0100100 )
b0101 *
#50000000
0%
#55000000
b0000000110 !
b0000000110 "
b0100000 #
b0110 $
1%
b0000000110 '
b0000000110 (
b0100000 )
b0110 *
#60000000
0%
#65000000
b0000000111 !
b0000000111 "
b0001111 #
b0111 $
1%
b0000000111 '
b0000000111 (
b0001111 )
b0111 *
#70000000
0%
#75000000
b0000001000 !
b0000001000 "
b0000000 #
b1000 $
1%
b0000001000 '
b0000001000 (
b0000000 )
b1000 *
#80000000
0%
#85000000
b0000001001 !
b0000001001 "
b0000100 #
b1001 $
1%
b0000001001 '
b0000001001 (
b0000100 )
b1001 *
#90000000
0%
#95000000
b0000001010 !
b0000001010 "
b0001000 #
b1010 $
1%
b0000001010 '
b0000001010 (
b0001000 )
b1010 *
#100000000
0%
#105000000
b0000001011 !
b0000001011 "
b1100000 #
b1011 $
1%
b0000001011 '
b0000001011 (
b1100000 )
b1011 *
#110000000
0%
#115000000
b0000001100 !
b0000001100 "
b0110001 #
b1100 $
1%
b0000001100 '
b0000001100 (
b0110001 )
b1100 *
#120000000
0%
#125000000
b0000001101 !
b0000001101 "
b1000010 #
b1101 $
1%
b0000001101 '
b0000001101 (
b1000010 )
b1101 *
#130000000
0%
#135000000
b0000001110 !
b0000001110 "
b0110000 #
b1110 $
1%
b0000001110 '
b0000001110 (
b0110000 )
b1110 *
#140000000
0%
#145000000
b0000001111 !
b0000001111 "
b0111000 #
b1111 $
1%
b0000001111 '
b0000001111 (
b0111000 )
b1111 *
#150000000
0%
#155000000
b0000010000 !
b0000010000 "
b0000001 #
b0000 $
1%
b0000010000 '
b0000010000 (
b0000001 )
b0000 *
#160000000
0%
#165000000
b0000010001 !
b0000010001 "
b1001111 #
b0001 $
1%
b0000010001 '
b0000010001 (
b1001111 )
b0001 *
#170000000
0%
#175000000
b0000010010 !
b0000010010 "
b0010010 #
b0010 $
1%
b0000010010 '
b0000010010 (
b0010010 )
b0010 *
#180000000
0%
#185000000
b0000010011 !
b0000010011 "
b0000110 #
b0011 $
1%
b0000010011 '
b0000010011 (
b0000110 )
b0011 *
#190000000
0%
#195000000
b0000010100 !
b0000010100 "
b1001100 #
b0100 $
1%
b0000010100 '
b0000010100 (
b1001100 )
b0100 *
#200000000
0%
#205000000
b0000010101 !
b0000010101 "
b0100100 #
b0101 $
1%
b0000010101 '
b0000010101 (
b0100100 )
b0101 *
#210000000
0%
#215000000
b0000010110 !
b0000010110 "
b0100000 #
b0110 $
1%
b0000010110 '
b0000010110 (
b0100000 )
b0110 *
#220000000
0%
#225000000
b0000010111 !
b0000010111 "
b0001111 #
b0111 $
1%
b0000010111 '
b0000010111 (
b0001111 )
b0111 *
#230000000
0%
#235000000
b0000011000 !
b0000011000 "
b0000000 #
b1000 $
1%
b0000011000 '
b0000011000 (
b0000000 )
b1000 *
#240000000
0%
#245000000
b0000011001 !
b0000011001 "
b0000100 #
b1001 $
1%
b0000011001 '
b0000011001 (
b0000100 )
b1001 *
#250000000
0%
#255000000
b0000011010 !
b0000011010 "
b0001000 #
b1010 $
1%
b0000011010 '
b0000011010 (
b0001000 )
b1010 *
#260000000
0%
#265000000
b0000011011 !
b0000011011 "
b1100000 #
b1011 $
1%
b0000011011 '
b0000011011 (
b1100000 )
b1011 *
#270000000
0%
#275000000
b0000011100 !
b0000011100 "
b0110001 #
b1100 $
1%
b0000011100 '
b0000011100 (
b0110001 )
b1100 *
#280000000
0%
#285000000
b0000011101 !
b0000011101 "
b1000010 #
b1101 $
1%
b0000011101 '
b0000011101 (
b1000010 )
b1101 *
#290000000
0%
#295000000
b0000011110 !
b0000011110 "
b0110000 #
b1110 $
1%
b0000011110 '
b0000011110 (
b0110000 )
b1110 *
#300000000
0%
#305000000
b0000011111 !
b0000011111 "
b0111000 #
b1111 $
1%
b0000011111 '
b0000011111 (
b0111000 )
b1111 *
#310000000
0%
#315000000
b0000100000 !
b0000100000 "
b0000001 #
b0000 $
1%
b0000100000 '
b0000100000 (
b0000001 )
b0000 *
#320000000
0%
#325000000
b0000100001 !
b0000100001 "
b1001111 #
b0001 $
1%
b0000100001 '
b0000100001 (
b1001111 )
b0001 *
#330000000
0%
#335000000
b0000100010 !
b0000100010 "
b0010010 #
b0010 $
1%
b0000100010 '
b0000100010 (
b0010010 )
b0010 *
#340000000
0%
#345000000
b0000100011 !
b0000100011 "
b0000110 #
b0011 $
1%
b0000100011 '
b0000100011 (
b0000110 )
b0011 *
#350000000
0%
#355000000
b0000100100 !
b0000100100 "
b1001100 #
b0100 $
1%
b0000100100 '
b0000100100 (
b1001100 )
b0100 *
#360000000
0%
#365000000
b0000100101 !
b0000100101 "
b0100100 #
b0101 $
1%
b0000100101 '
b0000100101 (
b0100100 )
b0101 *
#370000000
0%
#375000000
b0000100110 !
b0000100110 "
b0100000 #
b0110 $
1%
b0000100110 '
b0000100110 (
b0100000 )
b0110 *
#380000000
0%
#385000000
b0000100111 !
b0000100111 "
b0001111 #
b0111 $
1%
b0000100111 '
b0000100111 (
b0001111 )
b0111 *
#390000000
0%
#395000000
b0000101000 !
b0000101000 "
b0000000 #
b1000 $
1%
b0000101000 '
b0000101000 (
b0000000 )
b1000 *
#400000000
0%
#405000000
b0000101001 !
b0000101001 "
b0000100 #
b1001 $
1%
b0000101001 '
b0000101001 (
b0000100 )
b1001 *
#410000000
0%
#415000000
b0000101010 !
b0000101010 "
b0001000 #
b1010 $
1%
b0000101010 '
b0000101010 (
b0001000 )
b1010 *
#420000000
0%
#425000000
b0000101011 !
b0000101011 "
b1100000 #
b1011 $
1%
b0000101011 '
b0000101011 (
b1100000 )
b1011 *
#430000000
0%
#435000000
b0000101100 !
b0000101100 "
b0110001 #
b1100 $
1%
b0000101100 '
b0000101100 (
b0110001 )
b1100 *
#440000000
0%
#445000000
b0000101101 !
b0000101101 "
b1000010 #
b1101 $
1%
b0000101101 '
b0000101101 (
b1000010 )
b1101 *
#450000000
0%
#455000000
b0000101110 !
b0000101110 "
b0110000 #
b1110 $
1%
b0000101110 '
b0000101110 (
b0110000 )
b1110 *
#460000000
0%
#465000000
b0000101111 !
b0000101111 "
b0111000 #
b1111 $
1%
b0000101111 '
b0000101111 (
b0111000 )
b1111 *
#470000000
0%
#475000000
b0000110000 !
b0000110000 "
b0000001 #
b0000 $
1%
b0000110000 '
b0000110000 (
b0000001 )
b0000 *
#480000000
0%
#485000000
b0000110001 !
b0000110001 "
b1001111 #
b0001 $
1%
b0000110001 '
b0000110001 (
b1001111 )
b0001 *
#490000000
0%
#495000000
b0000110010 !
b0000110010 "
b0010010 #
b0010 $
1%
b0000110010 '
b0000110010 (
b0010010 )
b0010 *
#500000000
0%
#505000000
b0000110011 !
b0000110011 "
b0000110 #
b0011 $
1%
b0000110011 '
b0000110011 (
b0000110 )
b0011 *
#510000000
0%
#515000000
b0000110100 !
b0000110100 "
b1001100 #
b0100 $
1%
b0000110100 '
b0000110100 (
b1001100 )
b0100 *
#520000000
0%
#525000000
b0000110101 !
b0000110101 "
b0100100 #
b0101 $
1%
b0000110101 '
b0000110101 (
b0100100 )
b0101 *
#530000000
0%
#535000000
b0000110110 !
b0000110110 "
b0100000 #
b0110 $
1%
b0000110110 '
b0000110110 (
b0100000 )
b0110 *
#540000000
0%
#545000000
b0000110111 !
b0000110111 "
b0001111 #
b0111 $
1%
b0000110111 '
b0000110111 (
b0001111 )
b0111 *
#550000000
0%
#555000000
b0000111000 !
b0000111000 "
b0000000 #
b1000 $
1%
b0000111000 '
b0000111000 (
b0000000 )
b1000 *
#560000000
0%
#565000000
b0000111001 !
b0000111001 "
b0000100 #
b1001 $
1%
b0000111001 '
b0000111001 (
b0000100 )
b1001 *
#570000000
0%
#575000000
b0000111010 !
b0000111010 "
b0001000 #
b1010 $
1%
b0000111010 '
b0000111010 (
b0001000 )
b1010 *
#580000000
0%
#585000000
b0000111011 !
b0000111011 "
b1100000 #
b1011 $
1%
b0000111011 '
b0000111011 (
b1100000 )
b1011 *
#590000000
0%
#595000000
b0000111100 !
b0000111100 "
b0110001 #
b1100 $
1%
b0000111100 '
b0000111100 (
b0110001 )
b1100 *
#600000000
0%
#605000000
b0000111101 !
b0000111101 "
b1000010 #
b1101 $
1%
b0000111101 '
b0000111101 (
b1000010 )
b1101 *
#610000000
0%
#615000000
b0000111110 !
b0000111110 "
b0110000 #
b1110 $
1%
b0000111110 '
b0000111110 (
b0110000 )
b1110 *
#620000000
0%
#625000000
b0000111111 !
b0000111111 "
b0111000 #
b1111 $
1%
b0000111111 '
b0000111111 (
b0111000 )
b1111 *
#630000000
0%
#635000000
b0001000000 !
b0001000000 "
b0000001 #
b0000 $
1%
b0001000000 '
b0001000000 (
b0000001 )
b0000 *
#640000000
0%
#645000000
b0001000001 !
b0001000001 "
b1001111 #
b0001 $
1%
b0001000001 '
b0001000001 (
b1001111 )
b0001 *
#650000000
0%
#655000000
b0001000010 !
b0001000010 "
b0010010 #
b0010 $
1%
b0001000010 '
b0001000010 (
b0010010 )
b0010 *
#660000000
0%
#665000000
b0001000011 !
b0001000011 "
b0000110 #
b0011 $
1%
b0001000011 '
b0001000011 (
b0000110 )
b0011 *
#670000000
0%
#675000000
b0001000100 !
b0001000100 "
b1001100 #
b0100 $
1%
b0001000100 '
b0001000100 (
b1001100 )
b0100 *
#680000000
0%
#685000000
b0001000101 !
b0001000101 "
b0100100 #
b0101 $
1%
b0001000101 '
b0001000101 (
b0100100 )
b0101 *
#690000000
0%
#695000000
b0001000110 !
b0001000110 "
b0100000 #
b0110 $
1%
b0001000110 '
b0001000110 (
b0100000 )
b0110 *
#700000000
0%
#705000000
b0001000111 !
b0001000111 "
b0001111 #
b0111 $
1%
b0001000111 '
b0001000111 (
b0001111 )
b0111 *
#710000000
0%
#715000000
b0001001000 !
b0001001000 "
b0000000 #
b1000 $
1%
b0001001000 '
b0001001000 (
b0000000 )
b1000 *
#720000000
0%
#725000000
b0001001001 !
b0001001001 "
b0000100 #
b1001 $
1%
b0001001001 '
b0001001001 (
b0000100 )
b1001 *
#730000000
0%
#735000000
b0001001010 !
b0001001010 "
b0001000 #
b1010 $
1%
b0001001010 '
b0001001010 (
b0001000 )
b1010 *
#740000000
0%
#745000000
b0001001011 !
b0001001011 "
b1100000 #
b1011 $
1%
b0001001011 '
b0001001011 (
b1100000 )
b1011 *
#750000000
0%
#755000000
b0001001100 !
b0001001100 "
b0110001 #
b1100 $
1%
b0001001100 '
b0001001100 (
b0110001 )
b1100 *
#760000000
0%
#765000000
b0001001101 !
b0001001101 "
b1000010 #
b1101 $
1%
b0001001101 '
b0001001101 (
b1000010 )
b1101 *
#770000000
0%
#775000000
b0001001110 !
b0001001110 "
b0110000 #
b1110 $
1%
b0001001110 '
b0001001110 (
b0110000 )
b1110 *
#780000000
0%
#785000000
b0001001111 !
b0001001111 "
b0111000 #
b1111 $
1%
b0001001111 '
b0001001111 (
b0111000 )
b1111 *
#790000000
0%
#795000000
b0001010000 !
b0001010000 "
b0000001 #
b0000 $
1%
b0001010000 '
b0001010000 (
b0000001 )
b0000 *
#800000000
0%
#805000000
b0001010001 !
b0001010001 "
b1001111 #
b0001 $
1%
b0001010001 '
b0001010001 (
b1001111 )
b0001 *
#810000000
0%
#815000000
b0001010010 !
b0001010010 "
b0010010 #
b0010 $
1%
b0001010010 '
b0001010010 (
b0010010 )
b0010 *
#820000000
0%
#825000000
b0001010011 !
b0001010011 "
b0000110 #
b0011 $
1%
b0001010011 '
b0001010011 (
b0000110 )
b0011 *
#830000000
0%
#835000000
b0001010100 !
b0001010100 "
b1001100 #
b0100 $
1%
b0001010100 '
b0001010100 (
b1001100 )
b0100 *
#840000000
0%
#845000000
b0001010101 !
b0001010101 "
b0100100 #
b0101 $
1%
b0001010101 '
b0001010101 (
b0100100 )
b0101 *
#850000000
0%
#855000000
b0001010110 !
b0001010110 "
b0100000 #
b0110 $
1%
b0001010110 '
b0001010110 (
b0100000 )
b0110 *
#860000000
0%
#865000000
b0001010111 !
b0001010111 "
b0001111 #
b0111 $
1%
b0001010111 '
b0001010111 (
b0001111 )
b0111 *
#870000000
0%
#875000000
b0001011000 !
b0001011000 "
b0000000 #
b1000 $
1%
b0001011000 '
b0001011000 (
b0000000 )
b1000 *
#880000000
0%
#885000000
b0001011001 !
b0001011001 "
b0000100 #
b1001 $
1%
b0001011001 '
b0001011001 (
b0000100 )
b1001 *
#890000000
0%
#895000000
b0001011010 !
b0001011010 "
b0001000 #
b1010 $
1%
b0001011010 '
b0001011010 (
b0001000 )
b1010 *
#900000000
0%
#905000000
b0001011011 !
b0001011011 "
b1100000 #
b1011 $
1%
b0001011011 '
b0001011011 (
b1100000 )
b1011 *
#910000000
0%
#915000000
b0001011100 !
b0001011100 "
b0110001 #
b1100 $
1%
b0001011100 '
b0001011100 (
b0110001 )
b1100 *
#920000000
0%
#925000000
b0001011101 !
b0001011101 "
b1000010 #
b1101 $
1%
b0001011101 '
b0001011101 (
b1000010 )
b1101 *
#930000000
0%
#935000000
b0001011110 !
b0001011110 "
b0110000 #
b1110 $
1%
b0001011110 '
b0001011110 (
b0110000 )
b1110 *
#940000000
0%
#945000000
b0001011111 !
b0001011111 "
b0111000 #
b1111 $
1%
b0001011111 '
b0001011111 (
b0111000 )
b1111 *
#950000000
0%
#955000000
b0001100000 !
b0001100000 "
b0000001 #
b0000 $
1%
b0001100000 '
b0001100000 (
b0000001 )
b0000 *
#960000000
0%
#965000000
b0001100001 !
b0001100001 "
b1001111 #
b0001 $
1%
b0001100001 '
b0001100001 (
b1001111 )
b0001 *
#970000000
0%
#975000000
b0001100010 !
b0001100010 "
b0010010 #
b0010 $
1%
b0001100010 '
b0001100010 (
b0010010 )
b0010 *
#980000000
0%
#985000000
b0001100011 !
b0001100011 "
b0000110 #
b0011 $
1%
b0001100011 '
b0001100011 (
b0000110 )
b0011 *
#990000000
0%
#995000000
b0001100100 !
b0001100100 "
b1001100 #
b0100 $
1%
b0001100100 '
b0001100100 (
b1001100 )
b0100 *
#1000000000
0%
#1005000000
b0001100101 !
b0001100101 "
b0100100 #
b0101 $
1%
b0001100101 '
b0001100101 (
b0100100 )
b0101 *
#1010000000
0%
#1015000000
b0001100110 !
b0001100110 "
b0100000 #
b0110 $
1%
b0001100110 '
b0001100110 (
b0100000 )
b0110 *
#1020000000
0%
#1025000000
b0001100111 !
b0001100111 "
b0001111 #
b0111 $
1%
b0001100111 '
b0001100111 (
b0001111 )
b0111 *
#1030000000
0%
#1035000000
b0001101000 !
b0001101000 "
b0000000 #
b1000 $
1%
b0001101000 '
b0001101000 (
b0000000 )
b1000 *
#1040000000
0%
#1045000000
b0001101001 !
b0001101001 "
b0000100 #
b1001 $
1%
b0001101001 '
b0001101001 (
b0000100 )
b1001 *
#1050000000
0%
#1055000000
b0001101010 !
b0001101010 "
b0001000 #
b1010 $
1%
b0001101010 '
b0001101010 (
b0001000 )
b1010 *
#1060000000
0%
#1065000000
b0001101011 !
b0001101011 "
b1100000 #
b1011 $
1%
b0001101011 '
b0001101011 (
b1100000 )
b1011 *
#1070000000
0%
#1075000000
b0001101100 !
b0001101100 "
b0110001 #
b1100 $
1%
b0001101100 '
b0001101100 (
b0110001 )
b1100 *
#1080000000
0%
#1085000000
b0001101101 !
b0001101101 "
b1000010 #
b1101 $
1%
b0001101101 '
b0001101101 (
b1000010 )
b1101 *
#1090000000
0%
#1095000000
b0001101110 !
b0001101110 "
b0110000 #
b1110 $
1%
b0001101110 '
b0001101110 (
b0110000 )
b1110 *
#1100000000
0%
#1105000000
b0001101111 !
b0001101111 "
b0111000 #
b1111 $
1%
b0001101111 '
b0001101111 (
b0111000 )
b1111 *
#1110000000
0%
#1115000000
b0001110000 !
b0001110000 "
b0000001 #
b0000 $
1%
b0001110000 '
b0001110000 (
b0000001 )
b0000 *
#1120000000
0%
#1125000000
b0001110001 !
b0001110001 "
b1001111 #
b0001 $
1%
b0001110001 '
b0001110001 (
b1001111 )
b0001 *
#1130000000
0%
#1135000000
b0001110010 !
b0001110010 "
b0010010 #
b0010 $
1%
b0001110010 '
b0001110010 (
b0010010 )
b0010 *
#1140000000
0%
#1145000000
b0001110011 !
b0001110011 "
b0000110 #
b0011 $
1%
b0001110011 '
b0001110011 (
b0000110 )
b0011 *
#1150000000
0%
#1155000000
b0001110100 !
b0001110100 "
b1001100 #
b0100 $
1%
b0001110100 '
b0001110100 (
b1001100 )
b0100 *
#1160000000
0%
#1165000000
b0001110101 !
b0001110101 "
b0100100 #
b0101 $
1%
b0001110101 '
b0001110101 (
b0100100 )
b0101 *
#1170000000
0%
#1175000000
b0001110110 !
b0001110110 "
b0100000 #
b0110 $
1%
b0001110110 '
b0001110110 (
b0100000 )
b0110 *
#1180000000
0%
#1185000000
b0001110111 !
b0001110111 "
b0001111 #
b0111 $
1%
b0001110111 '
b0001110111 (
b0001111 )
b0111 *
#1190000000
0%
#1195000000
b0001111000 !
b0001111000 "
b0000000 #
b1000 $
1%
b0001111000 '
b0001111000 (
b0000000 )
b1000 *
#1200000000
0%
#1205000000
b0001111001 !
b0001111001 "
b0000100 #
b1001 $
1%
b0001111001 '
b0001111001 (
b0000100 )
b1001 *
#1210000000
0%
#1215000000
b0001111010 !
b0001111010 "
b0001000 #
b1010 $
1%
b0001111010 '
b0001111010 (
b0001000 )
b1010 *
#1220000000
0%
#1225000000
b0001111011 !
b0001111011 "
b1100000 #
b1011 $
1%
b0001111011 '
b0001111011 (
b1100000 )
b1011 *
#1230000000
0%
#1235000000
b0001111100 !
b0001111100 "
b0110001 #
b1100 $
1%
b0001111100 '
b0001111100 (
b0110001 )
b1100 *
#1240000000
0%
#1245000000
b0001111101 !
b0001111101 "
b1000010 #
b1101 $
1%
b0001111101 '
b0001111101 (
b1000010 )
b1101 *
#1250000000
0%
#1255000000
b0001111110 !
b0001111110 "
b0110000 #
b1110 $
1%
b0001111110 '
b0001111110 (
b0110000 )
b1110 *
#1260000000
0%
#1265000000
b0001111111 !
b0001111111 "
b0111000 #
b1111 $
1%
b0001111111 '
b0001111111 (
b0111000 )
b1111 *
#1270000000
0%
#1275000000
b0010000000 !
b0010000000 "
b0000001 #
b0000 $
1%
b0010000000 '
b0010000000 (
b0000001 )
b0000 *
#1280000000
0%
#1285000000
b0010000001 !
b0010000001 "
b1001111 #
b0001 $
1%
b0010000001 '
b0010000001 (
b1001111 )
b0001 *
#1290000000
0%
#1295000000
b0010000010 !
b0010000010 "
b0010010 #
b0010 $
1%
b0010000010 '
b0010000010 (
b0010010 )
b0010 *
#1300000000
0%
#1305000000
b0010000011 !
b0010000011 "
b0000110 #
b0011 $
1%
b0010000011 '
b0010000011 (
b0000110 )
b0011 *
#1310000000
0%
#1315000000
b0010000100 !
b0010000100 "
b1001100 #
b0100 $
1%
b0010000100 '
b0010000100 (
b1001100 )
b0100 *
#1320000000
0%
#1325000000
b0010000101 !
b0010000101 "
b0100100 #
b0101 $
1%
b0010000101 '
b0010000101 (
b0100100 )
b0101 *
#1330000000
0%
#1335000000
b0010000110 !
b0010000110 "
b0100000 #
b0110 $
1%
b0010000110 '
b0010000110 (
b0100000 )
b0110 *
#1340000000
0%
#1345000000
b0010000111 !
b0010000111 "
b0001111 #
b0111 $
1%
b0010000111 '
b0010000111 (
b0001111 )
b0111 *
#1350000000
0%
#1355000000
b0010001000 !
b0010001000 "
b0000000 #
b1000 $
1%
b0010001000 '
b0010001000 (
b0000000 )
b1000 *
#1360000000
0%
#1365000000
b0010001001 !
b0010001001 "
b0000100 #
b1001 $
1%
b0010001001 '
b0010001001 (
b0000100 )
b1001 *
#1370000000
0%
#1375000000
b0010001010 !
b0010001010 "
b0001000 #
b1010 $
1%
b0010001010 '
b0010001010 (
b0001000 )
b1010 *
#1380000000
0%
#1385000000
b0010001011 !
b0010001011 "
b1100000 #
b1011 $
1%
b0010001011 '
b0010001011 (
b1100000 )
b1011 *
#1390000000
0%
#1395000000
b0010001100 !
b0010001100 "
b0110001 #
b1100 $
1%
b0010001100 '
b0010001100 (
b0110001 )
b1100 *
#1400000000
0%
#1405000000
b0010001101 !
b0010001101 "
b1000010 #
b1101 $
1%
b0010001101 '
b0010001101 (
b1000010 )
b1101 *
#1410000000
0%
#1415000000
b0010001110 !
b0010001110 "
b0110000 #
b1110 $
1%
b0010001110 '
b0010001110 (
b0110000 )
b1110 *
#1420000000
0%
#1425000000
b0010001111 !
b0010001111 "
b0111000 #
b1111 $
1%
b0010001111 '
b0010001111 (
b0111000 )
b1111 *
#1430000000
0%
#1435000000
b0010010000 !
b0010010000 "
b0000001 #
b0000 $
1%
b0010010000 '
b0010010000 (
b0000001 )
b0000 *
#1440000000
0%
#1445000000
b0010010001 !
b0010010001 "
b1001111 #
b0001 $
1%
b0010010001 '
b0010010001 (
b1001111 )
b0001 *
#1450000000
0%
#1455000000
b0010010010 !
b0010010010 "
b0010010 #
b0010 $
1%
b0010010010 '
b0010010010 (
b0010010 )
b0010 *
#1460000000
0%
#1465000000
b0010010011 !
b0010010011 "
b0000110 #
b0011 $
1%
b0010010011 '
b0010010011 (
b0000110 )
b0011 *
#1470000000
0%
#1475000000
b0010010100 !
b0010010100 "
b1001100 #
b0100 $
1%
b0010010100 '
b0010010100 (
b1001100 )
b0100 *
#1480000000
0%
#1485000000
b0010010101 !
b0010010101 "
b0100100 #
b0101 $
1%
b0010010101 '
b0010010101 (
b0100100 )
b0101 *
#1490000000
0%
#1495000000
b0010010110 !
b0010010110 "
b0100000 #
b0110 $
1%
b0010010110 '
b0010010110 (
b0100000 )
b0110 *
#1500000000
0%
#1505000000
b0010010111 !
b0010010111 "
b0001111 #
b0111 $
1%
b0010010111 '
b0010010111 (
b0001111 )
b0111 *
#1510000000
0%
#1515000000
b0010011000 !
b0010011000 "
b0000000 #
b1000 $
1%
b0010011000 '
b0010011000 (
b0000000 )
b1000 *
#1520000000
0%
#1525000000
b0010011001 !
b0010011001 "
b0000100 #
b1001 $
1%
b0010011001 '
b0010011001 (
b0000100 )
b1001 *
#1530000000
0%
#1535000000
b0010011010 !
b0010011010 "
b0001000 #
b1010 $
1%
b0010011010 '
b0010011010 (
b0001000 )
b1010 *
#1540000000
0%
#1545000000
b0010011011 !
b0010011011 "
b1100000 #
b1011 $
1%
b0010011011 '
b0010011011 (
b1100000 )
b1011 *
#1550000000
0%
#1555000000
b0010011100 !
b0010011100 "
b0110001 #
b1100 $
1%
b0010011100 '
b0010011100 (
b0110001 )
b1100 *
#1560000000
0%
#1565000000
b0010011101 !
b0010011101 "
b1000010 #
b1101 $
1%
b0010011101 '
b0010011101 (
b1000010 )
b1101 *
#1570000000
0%
#1575000000
b0010011110 !
b0010011110 "
b0110000 #
b1110 $
1%
b0010011110 '
b0010011110 (
b0110000 )
b1110 *
#1580000000
0%
#1585000000
b0010011111 !
b0010011111 "
b0111000 #
b1111 $
1%
b0010011111 '
b0010011111 (
b0111000 )
b1111 *
#1590000000
0%
#1595000000
b0010100000 !
b0010100000 "
b0000001 #
b0000 $
1%
b0010100000 '
b0010100000 (
b0000001 )
b0000 *
#1600000000
0%
#1605000000
b0010100001 !
b0010100001 "
b1001111 #
b0001 $
1%
b0010100001 '
b0010100001 (
b1001111 )
b0001 *
#1610000000
0%
#1615000000
b0010100010 !
b0010100010 "
b0010010 #
b0010 $
1%
b0010100010 '
b0010100010 (
b0010010 )
b0010 *
#1620000000
0%
#1625000000
b0010100011 !
b0010100011 "
b0000110 #
b0011 $
1%
b0010100011 '
b0010100011 (
b0000110 )
b0011 *
#1630000000
0%
#1635000000
b0010100100 !
b0010100100 "
b1001100 #
b0100 $
1%
b0010100100 '
b0010100100 (
b1001100 )
b0100 *
#1640000000
0%
#1645000000
b0010100101 !
b0010100101 "
b0100100 #
b0101 $
1%
b0010100101 '
b0010100101 (
b0100100 )
b0101 *
#1650000000
0%
#1655000000
b0010100110 !
b0010100110 "
b0100000 #
b0110 $
1%
b0010100110 '
b0010100110 (
b0100000 )
b0110 *
#1660000000
0%
#1665000000
b0010100111 !
b0010100111 "
b0001111 #
b0111 $
1%
b0010100111 '
b0010100111 (
b0001111 )
b0111 *
#1670000000
0%
#1675000000
b0010101000 !
b0010101000 "
b0000000 #
b1000 $
1%
b0010101000 '
b0010101000 (
b0000000 )
b1000 *
#1680000000
0%
#1685000000
b0010101001 !
b0010101001 "
b0000100 #
b1001 $
1%
b0010101001 '
b0010101001 (
b0000100 )
b1001 *
#1690000000
0%
#1695000000
b0010101010 !
b0010101010 "
b0001000 #
b1010 $
1%
b0010101010 '
b0010101010 (
b0001000 )
b1010 *
#1700000000
0%
#1705000000
b0010101011 !
b0010101011 "
b1100000 #
b1011 $
1%
b0010101011 '
b0010101011 (
b1100000 )
b1011 *
#1710000000
0%
